README.md
setup.cfg
setup.py
pkg/__init__.py
pkg/main.py
pylint_hook.egg-info/PKG-INFO
pylint_hook.egg-info/SOURCES.txt
pylint_hook.egg-info/dependency_links.txt
pylint_hook.egg-info/entry_points.txt
pylint_hook.egg-info/requires.txt
pylint_hook.egg-info/top_level.txt