Metadata-Version: 2.1
Name: pylint-hook
Version: 2.1.2
Summary: A Git hook that works based on Pylint evaluation
Author: Alla Makhotka
Author-email: all.mahotka2012@yandex.ru
